ddqla/__init__.py
ddqla/agents/__init__.py
ddqla/agents/base_agent.py
ddqla-0.1.25.dist-info/METADATA
ddqla-0.1.25.dist-info/WHEEL
ddqla-0.1.25.dist-info/licenses/LICENSE
ddqla-0.1.25.dist-info/RECORD
