Metadata-Version: 2.1
Name: ddqla
Version: 0.1.25
Summary: A smart way to create a ddql agent
Project-URL: Homepage, https://github.com/marco-sarti/ddqla
Project-URL: Bug Tracker, https://github.com/marco-sarti/ddqla/issues
Author-email: Marco Sarti <info@marcosarti.com>
License-File: LICENSE
Classifier: License :: OSI Approved :: Apache Software License
Classifier: Operating System :: OS Independent
Classifier: Programming Language :: Python :: 3
Requires-Python: >=3.10
